MANIFEST.in
README.rst
RELEASE-VERSION
git_version.py
setup.cfg
setup.py
spec_version.py
ev3dev/GyroBalancer.py
ev3dev/__init__.py
ev3dev/auto.py
ev3dev/brickpi.py
ev3dev/core.py
ev3dev/ev3.py
ev3dev/framebuffer.py
ev3dev/helper.py
ev3dev/version.py
ev3dev/virtualterminal.py
ev3dev/webserver.py
ev3dev/fonts/__init__.py
python_ev3dev.egg-info/PKG-INFO
python_ev3dev.egg-info/SOURCES.txt
python_ev3dev.egg-info/dependency_links.txt
python_ev3dev.egg-info/requires.txt
python_ev3dev.egg-info/top_level.txt