Metadata-Version: 1.0
Name: python-ev3dev
Version: 0.8.1
Summary: Python language bindings for ev3dev
Home-page: https://github.com/rhempel/ev3dev-lang-python
Author: Ralph Hempel
Author-email: rhempel@hempeldesigngroup.com
License: MIT
Platform: UNKNOWN
